CHANGES.md
LICENSE
MANIFEST.in
README.rst
setup.py
ScrappyServer.egg-info/PKG-INFO
ScrappyServer.egg-info/SOURCES.txt
ScrappyServer.egg-info/dependency_links.txt
ScrappyServer.egg-info/requires.txt
ScrappyServer.egg-info/top_level.txt
scrappyserver/__init__.py
scrappyserver/default_settings.py
scrappyserver/endpoints.py
scrappyserver/exceptions.py
scrappyserver/extensions.py
scrappyserver/flaskapp.py
scrappyserver/scrapy_utils.py
scrappyserver/tests/BaseFlaskApp.py
scrappyserver/tests/__init__.py
scrappyserver/tests/custom_endpoints.py
scrappyserver/tests/test_default_settings.py
scrappyserver/tests/test_endpoints.py
scrappyserver/tests/test_extensions.py
scrappyserver/tests/test_flaskapp.py
scrappyserver/tests/test_scrapy_utils.py
scrappyserver/tests/test_settings.py