Metadata-Version: 1.0
Name: ScrappyServer
Version: 0.0.0.1
Summary: API for Scrapy spiders
Home-page: https://github.com/dmkitui/arachne
Author: Chanticleer
Author-email: dmkitui@gmail.com
License: BSD
Platform: UNKNOWN
